genlayer_py/__init__.py
genlayer_py/assertions.py
genlayer_py/exceptions.py
genlayer_py/logging.py
genlayer_py/abi/__init__.py
genlayer_py/abi/transactions.py
genlayer_py/abi/calldata/__init__.py
genlayer_py/abi/calldata/consts.py
genlayer_py/abi/calldata/decoder.py
genlayer_py/abi/calldata/encoder.py
genlayer_py/abi/calldata/string.py
genlayer_py/accounts/__init__.py
genlayer_py/accounts/account.py
genlayer_py/accounts/actions.py
genlayer_py/chains/__init__.py
genlayer_py/chains/actions.py
genlayer_py/chains/localnet.py
genlayer_py/chains/studionet.py
genlayer_py/chains/testnet_asimov.py
genlayer_py/client/__init__.py
genlayer_py/client/client.py
genlayer_py/client/genlayer_client.py
genlayer_py/config/__init__.py
genlayer_py/config/transactions.py
genlayer_py/consensus/__init__.py
genlayer_py/consensus/abi/__init__.py
genlayer_py/consensus/abi/consensus_data_abi.json
genlayer_py/consensus/abi/consensus_main_abi.json
genlayer_py/consensus/consensus_main/__init__.py
genlayer_py/consensus/consensus_main/decoder.py
genlayer_py/consensus/consensus_main/encoder.py
genlayer_py/contracts/__init__.py
genlayer_py/contracts/actions.py
genlayer_py/contracts/utils.py
genlayer_py/provider/__init__.py
genlayer_py/provider/provider.py
genlayer_py/transactions/__init__.py
genlayer_py/transactions/actions.py
genlayer_py/types/__init__.py
genlayer_py/types/calldata.py
genlayer_py/types/chain.py
genlayer_py/types/contracts.py
genlayer_py/types/transactions.py
genlayer_py/utils/__init__.py
genlayer_py/utils/jsonifier.py
genlayer_py-0.9.2.dist-info/licenses/LICENSE
genlayer_py-0.9.2.dist-info/METADATA
genlayer_py-0.9.2.dist-info/WHEEL
genlayer_py-0.9.2.dist-info/top_level.txt
genlayer_py-0.9.2.dist-info/RECORD
