Metadata-Version: 2.4
Name: genlayer-py
Version: 0.9.2
Summary: GenLayer Python SDK
Author: GenLayer
License-Expression: MIT
Classifier: Development Status :: 4 - Beta
Classifier: Intended Audience :: Developers
Classifier: Programming Language :: Python :: 3
Classifier: Programming Language :: Python :: 3.12
Classifier: Programming Language :: Python :: 3.13
Requires-Python: >=3.12
License-File: LICENSE
Requires-Dist: web3>=7.10.0
Dynamic: license-file
